[{"cluster": 0, "weight": 2.985096870342772, "name": "Julie's Healthy Cafe", "y": -122.2576502, "x": 37.8689097}, {"cluster": 0, "weight": 1.9135618479880776, "name": "Quickly", "y": -122.2522884, "x": 37.8686878}, {"cluster": 0, "weight": 1.9135618479880776, "name": "Sweetheart Cafe", "y": -122.2579199, "x": 37.8681116}, {"cluster": 1, "weight": 2.985096870342772, "name": "Cafe Rio", "y": -122.2666688, "x": 37.8704977}, {"cluster": 1, "weight": 1.9135618479880776, "name": "T C Garden Restaurant", "y": -122.2597581, "x": 37.8752015}, {"cluster": 1, "weight": 2.985096870342772, "name": "Punjabi By Nature", "y": -122.2658691, "x": 37.8701853}, {"cluster": 0, "weight": 2.985096870342772, "name": "Mandarin House", "y": -122.2580885, "x": 37.868144}, {"cluster": 0, "weight": 3.0, "name": "Saigon Eats", "y": -122.259748, "x": 37.8686684}, {"cluster": 1, "weight": 2.985096870342772, "name": "Nefeli Caffe", "y": -122.2601952, "x": 37.8754083}, {"cluster": 1, "weight": 2.985096870342772, "name": "The Stuffed Inn", "y": -122.26004, "x": 37.8756879}, {"cluster": 0, "weight": 4.5, "name": "Musical Offering", "y": -122.260698, "x": 37.868429}, {"cluster": 0, "weight": 5.1281669150521605, "name": "Freehouse", "y": -122.254269, "x": 37.868961}, {"cluster": 0, "weight": 2.985096870342772, "name": "Gordo Taqueria", "y": -122.2588129, "x": 37.86684}, {"cluster": 1, "weight": 5.1281669150521605, "name": "Celia's", "y": -122.259984, "x": 37.8755809}, {"cluster": 0, "weight": 3.0, "name": "Bear's Ramen House", "y": -122.2580151, "x": 37.8680531}, {"cluster": 0, "weight": 1.9135618479880776, "name": "The Bear's Lair Brew Pub", "y": -122.259871959686, "x": 37.8689927193298}, {"cluster": 0, "weight": 2.985096870342772, "name": "Lotus House", "y": -122.258216, "x": 37.868035}, {"cluster": 1, "weight": 3.0, "name": "Momo Masala", "y": -122.2598181, "x": 37.8751965}, {"cluster": 1, "weight": 2.985096870342772, "name": "Gomnaru Restaurant", "y": -122.2598373, "x": 37.87524}, {"cluster": 0, "weight": 1.9135618479880776, "name": "Taco Truck", "y": -122.256421, "x": 37.869201}, {"cluster": 0, "weight": 2.985096870342772, "name": "Tako Sushi", "y": -122.2588314, "x": 37.8671581}, {"cluster": 0, "weight": 4.5, "name": "Stella Nonna Milwaukee Fish Fry", "y": -122.262428, "x": 37.86541}, {"cluster": 0, "weight": 1.9135618479880776, "name": "Top Dog", "y": -122.2574328, "x": 37.8678945}, {"cluster": 0, "weight": 1.9135618479880776, "name": "Pasta-In-A-Box", "y": -122.2588542, "x": 37.8672496}, {"cluster": 0, "weight": 2.985096870342772, "name": "Naan N Curry", "y": -122.2590685, "x": 37.8673999}, {"cluster": 0, "weight": 5.1281669150521605, "name": "Joshu-Ya Brasserie", "y": -122.2593812, "x": 37.8652343}, {"cluster": 1, "weight": 2.0, "name": "Top Dog 2", "y": -122.2597386, "x": 37.8752327}, {"cluster": 0, "weight": 2.985096870342772, "name": "Ann's Kitchen", "y": -122.2586396, "x": 37.8651779}, {"cluster": 0, "weight": 1.9135618479880776, "name": "Mediterraneam Caffe", "y": -122.258338, "x": 37.865614}, {"cluster": 0, "weight": 1.9135618479880776, "name": "Durant Square - Asian Ghetto", "y": -122.2579783, "x": 37.8680781}, {"cluster": 1, "weight": 2.985096870342772, "name": "Cinnaholic", "y": -122.2659014, "x": 37.8702006}, {"cluster": 0, "weight": 5.1281669150521605, "name": "Berkeley Thai House", "y": -122.2583894, "x": 37.8670609}, {"cluster": 0, "weight": 2.985096870342772, "name": "Smart Alec's Intelligent Food", "y": -122.2589892, "x": 37.8677549}, {"cluster": 1, "weight": 1.9135618479880776, "name": "Berkeley Floor Cafe", "y": -122.2648949, "x": 37.8679837}, {"cluster": 1, "weight": 1.9135618479880776, "name": "Pat Brown's Grill", "y": -122.264895737171, "x": 37.8733141647778}, {"cluster": 1, "weight": 3.0, "name": "Northside Cafe", "y": -122.2601962, "x": 37.8752289}, {"cluster": 0, "weight": 2.985096870342772, "name": "Indian Flavors Express", "y": -122.2582208, "x": 37.8688198}, {"cluster": 0, "weight": 1.9135618479880776, "name": "Cafe Espresso Experience", "y": -122.2606426, "x": 37.8684351}, {"cluster": 0, "weight": 1.9135618479880776, "name": "Planet Kebob & Cafe", "y": -122.2599315, "x": 37.8678328}, {"cluster": 1, "weight": 2.985096870342772, "name": "Hummingbird Express", "y": -122.2602129, "x": 37.8755024}, {"cluster": 0, "weight": 1.9135618479880776, "name": "Crossroads", "y": -122.2563918, "x": 37.8666266}, {"cluster": 0, "weight": 1.9135618479880776, "name": "Fat Slice Pizza", "y": -122.258583, "x": 37.867209}, {"cluster": 0, "weight": 2.985096870342772, "name": "The Melt Berkeley", "y": -122.2589718, "x": 37.8668273}, {"cluster": 1, "weight": 2.5, "name": "La Val's Pizza", "y": -122.2603641, "x": 37.8755322}, {"cluster": 0, "weight": 1.9135618479880776, "name": "The Toaster Oven", "y": -122.2590117, "x": 37.8684118}, {"cluster": 1, "weight": 2.985096870342772, "name": "Hummingbird Cafe", "y": -122.2603537, "x": 37.8754914}, {"cluster": 1, "weight": 1.9135618479880776, "name": "Top Dog 3", "y": -122.2663412, "x": 37.8705286}, {"cluster": 0, "weight": 2.985096870342772, "name": "Cafe Durant", "y": -122.2583343, "x": 37.8680114}, {"cluster": 0, "weight": 1.9135618479880776, "name": "Foley's Deli", "y": -122.259354, "x": 37.868272}, {"cluster": 0, "weight": 2.985096870342772, "name": "Happy Valley", "y": -122.2584562, "x": 37.8650499}, {"cluster": 0, "weight": 1.9135618479880776, "name": "Sunrise Deli", "y": -122.260181, "x": 37.8683059}, {"cluster": 0, "weight": 1.9135618479880776, "name": "Caffe Mediterraneum", "y": -122.2584692, "x": 37.8655821}, {"cluster": 0, "weight": 2.985096870342772, "name": "Wing Fiesta", "y": -122.2597479, "x": 37.8686679}, {"cluster": 0, "weight": 1.9135618479880776, "name": "Chang Luong Restaurant", "y": -122.2582906, "x": 37.8680415}, {"cluster": 0, "weight": 2.985096870342772, "name": "Thai Basil Cuisine", "y": -122.2581241, "x": 37.8680259}, {"cluster": 0, "weight": 2.985096870342772, "name": "T-Toust", "y": -122.2598048, "x": 37.8678782}, {"cluster": 0, "weight": 2.985096870342772, "name": "La Burrita", "y": -122.2575506, "x": 37.8679766}, {"cluster": 0, "weight": 1.9135618479880776, "name": "Bongo Burger 3", "y": -122.2582112, "x": 37.8652379}, {"cluster": 0, "weight": 1.5, "name": "Cheese 'N' Stuff", "y": -122.2595445, "x": 37.8677205}, {"cluster": 0, "weight": 1.9135618479880776, "name": "Subway", "y": -122.2594514, "x": 37.8686641}, {"cluster": 0, "weight": 2.985096870342772, "name": "Pappy's Grill & Sports Bar", "y": -122.2588366, "x": 37.8674301}, {"cluster": 0, "weight": 1.9135618479880776, "name": "Crepes A-Go Go", "y": -122.2591694, "x": 37.8679211}, {"cluster": 1, "weight": 4.0566318926974665, "name": "C U Sushi", "y": -122.2664781, "x": 37.8705095}, {"cluster": 0, "weight": 1.9135618479880776, "name": "Ramona's Caf\u00e9", "y": -122.254925966263, "x": 37.8705256863629}, {"cluster": 0, "weight": 1.9135618479880776, "name": "UCafe", "y": -122.2569545, "x": 37.8680197}, {"cluster": 1, "weight": 4.0566318926974665, "name": "The Pho Bar", "y": -122.2602704, "x": 37.8756137}, {"cluster": 0, "weight": 1.9135618479880776, "name": "Cafe Milano", "y": -122.258495, "x": 37.868511}, {"cluster": 0, "weight": 1.9135618479880776, "name": "Jimmie Beans Fifo Cafe", "y": -122.2527946, "x": 37.8711657}, {"cluster": 0, "weight": 5.0, "name": "Koryo Restaurant", "y": -122.258941, "x": 37.863919}, {"cluster": 0, "weight": 2.985096870342772, "name": "Tivoli Caffe", "y": -122.2578299, "x": 37.8688691}, {"cluster": 0, "weight": 2.985096870342772, "name": "House of Curries", "y": -122.257913, "x": 37.8678087}, {"cluster": 1, "weight": 1.9135618479880776, "name": "Bongo Burger", "y": -122.266394, "x": 37.870404}, {"cluster": 0, "weight": 3.5, "name": "Pho K & K", "y": -122.2582558, "x": 37.8644503}, {"cluster": 0, "weight": 2.5, "name": "Cupkates", "y": -122.2625529, "x": 37.8654727}, {"cluster": 1, "weight": 2.985096870342772, "name": "La Burrita 2", "y": -122.2602616, "x": 37.8755679}, {"cluster": 0, "weight": 2.985096870342772, "name": "Le Petit Cheval", "y": -122.2567822, "x": 37.8689555}, {"cluster": 0, "weight": 1.9135618479880776, "name": "Dojo Dog", "y": -122.2596091, "x": 37.8690986}, {"cluster": 0, "weight": 1.0, "name": "Cafe 3", "y": -122.260408, "x": 37.867417}, {"cluster": 1, "weight": 4.0566318926974665, "name": "Saturn Cafe", "y": -122.2659885, "x": 37.8698214}, {"cluster": 0, "weight": 3.0, "name": "Sun Hong Kong Restaurant", "y": -122.2595134, "x": 37.86788}, {"cluster": 0, "weight": 2.985096870342772, "name": "Racha Cafe", "y": -122.2584731, "x": 37.8647594}, {"cluster": 0, "weight": 1.9135618479880776, "name": "Turkish Kitchen Express", "y": -122.258741, "x": 37.8670856}, {"cluster": 0, "weight": 4.5, "name": "Henry's", "y": -122.256618440151, "x": 37.8680398922584}, {"cluster": 0, "weight": 4.0, "name": "Fondue Fred", "y": -122.25894, "x": 37.863919}, {"cluster": 0, "weight": 1.5, "name": "Chinese Express", "y": -122.2592389, "x": 37.8667955}, {"cluster": 0, "weight": 1.9135618479880776, "name": "Coffee Source", "y": -122.2587734, "x": 37.8668408}, {"cluster": 0, "weight": 4.5, "name": "Golden Bear Cafe", "y": -122.259603738785, "x": 37.8698057886903}, {"cluster": 0, "weight": 1.9135618479880776, "name": "Peking Express", "y": -122.2581978, "x": 37.867768}, {"cluster": 1, "weight": 2.985096870342772, "name": "La Cascada Taqueria", "y": -122.2663047, "x": 37.8705337}, {"cluster": 0, "weight": 1.9135618479880776, "name": "La Fiesta Mexican Restaurant", "y": -122.25802, "x": 37.865831}, {"cluster": 1, "weight": 5.0, "name": "Alborz", "y": -122.266645, "x": 37.8701999}, {"cluster": 0, "weight": 1.9135618479880776, "name": "The Little Dipper Chocolate Company", "y": -122.2591719, "x": 37.868725}, {"cluster": 0, "weight": 1.9135618479880776, "name": "Cal Gyro Mediterranean", "y": -122.258034, "x": 37.868212}, {"cluster": 1, "weight": 2.985096870342772, "name": "Viengvilay Thai Cuisine", "y": -122.2600721, "x": 37.8751579}, {"cluster": 1, "weight": 2.985096870342772, "name": "Urbann Turbann", "y": -122.2602072, "x": 37.8752855}, {"cluster": 1, "weight": 1.9135618479880776, "name": "Free Speech Movement Cafe", "y": -122.260690033436, "x": 37.8724079738015}, {"cluster": 0, "weight": 2.985096870342772, "name": "KoKo Express", "y": -122.2597653, "x": 37.8677755}, {"cluster": 0, "weight": 2.985096870342772, "name": "Chipotle Mexican Grill", "y": -122.2590498, "x": 37.8683664}, {"cluster": 1, "weight": 1.5, "name": "Zach's Snacks", "y": -122.2601606, "x": 37.8752481}, {"cluster": 0, "weight": 1.9135618479880776, "name": "The Coffee Lab", "y": -122.255591154098, "x": 37.8727784971583}, {"cluster": 1, "weight": 1.9135618479880776, "name": "Suya African Caribbean Grill", "y": -122.2658652, "x": 37.8703067}, {"cluster": 0, "weight": 2.985096870342772, "name": "Pasta Bene", "y": -122.2585639, "x": 37.8639919}, {"cluster": 0, "weight": 2.985096870342772, "name": "Remy's Mexican Restaurant", "y": -122.2580606, "x": 37.866061}, {"cluster": 0, "weight": 1.9135618479880776, "name": "Peets Coffee & Tea", "y": -122.2561597, "x": 37.8670297}, {"cluster": 1, "weight": 2.985096870342772, "name": "Vinnie's Cheesesteaks", "y": -122.2602115, "x": 37.8753118}, {"cluster": 1, "weight": 1.9135618479880776, "name": "Bongo Burger 2", "y": -122.2602229, "x": 37.8755712}, {"cluster": 0, "weight": 5.0, "name": "Babette", "y": -122.2565107, "x": 37.8681313}, {"cluster": 0, "weight": 2.985096870342772, "name": "Souvlaki Greek Traditional Food", "y": -122.2582955, "x": 37.8677974}, {"cluster": 0, "weight": 2.985096870342772, "name": "Manhattan Roast & Grill", "y": -122.2582175, "x": 37.8677609}, {"cluster": 0, "weight": 2.0, "name": "I.B.'s Hoagies", "y": -122.25849, "x": 37.868041}, {"cluster": 1, "weight": 5.1281669150521605, "name": "Gather", "y": -122.26602, "x": 37.869348}, {"cluster": 0, "weight": 1.9135618479880776, "name": "Cafe Zeb", "y": -122.2535688, "x": 37.8694291}, {"cluster": 0, "weight": 1.9135618479880776, "name": "Blondie's Pizza", "y": -122.2591966, "x": 37.8680339}, {"cluster": 0, "weight": 1.9135618479880776, "name": "Sam's Market", "y": -122.259359, "x": 37.868292}, {"cluster": 0, "weight": 1.9135618479880776, "name": "D'Yar", "y": -122.2585448, "x": 37.8678828}, {"cluster": 1, "weight": 3.0, "name": "Jasmine Thai", "y": -122.2602981, "x": 37.8759615}, {"cluster": 0, "weight": 4.0566318926974665, "name": "Desi Dog by Brazil Cafe", "y": -122.2589321, "x": 37.8687725}, {"cluster": 0, "weight": 2.985096870342772, "name": "San Francisco Soup Company", "y": -122.258869, "x": 37.868755}, {"cluster": 0, "weight": 2.985096870342772, "name": "Thai Noodle II", "y": -122.2588162, "x": 37.8664181}, {"cluster": 0, "weight": 2.985096870342772, "name": "International House Cafe", "y": -122.2519943, "x": 37.8695199}]